amhelpers/__init__.py
amhelpers/amhelpers.py
amhelpers/config_parsing.py
amhelpers/metrics.py
amhelpers/sweep.py
amhelpers-0.5.6.dist-info/LICENSE
amhelpers-0.5.6.dist-info/METADATA
amhelpers-0.5.6.dist-info/WHEEL
amhelpers-0.5.6.dist-info/RECORD
