Metadata-Version: 2.1
Name: amhelpers
Version: 0.5.6
Summary: A collection of handy utilities.
License: MIT
Author: Anton Matsson
Requires-Python: >=3.8
Classifier: License :: OSI Approved :: MIT License
Classifier: Programming Language :: Python :: 3
Classifier: Programming Language :: Python :: 3.8
Classifier: Programming Language :: Python :: 3.9
Classifier: Programming Language :: Python :: 3.10
Classifier: Programming Language :: Python :: 3.11
Requires-Dist: gitpython (>=3.1.32,<4.0.0)
Requires-Dist: pandas (>=1.4.0)
Requires-Dist: pyyaml (>=6.0.0,<7.0.0)
